pythonidae/__init__.py
pythonidae/parser.py
pythonidae/request.py
pythonidae/response.py
pythonidae/router.py
pythonidae-4.0.0.dist-info/LICENCE
pythonidae-4.0.0.dist-info/METADATA
pythonidae-4.0.0.dist-info/WHEEL
pythonidae-4.0.0.dist-info/top_level.txt
pythonidae-4.0.0.dist-info/RECORD
