Metadata-Version: 2.1
Name: pythonidae
Version: 4.0.0
Summary: Fast, minimalist web framework for Python
Home-page: UNKNOWN
Author: parthka, sai, thehelkaproject
Author-email: parthka.2005@gmail.com
License: UNKNOWN
Keywords: python,pythonidae,website,web framework,http
Platform: UNKNOWN
Classifier: Programming Language :: Python :: 3
Classifier: Operating System :: OS Independent
Requires-Dist: jinja2
